winapiclient/__init__.py
winapiclient/winapiclient.py
WinAPIClient-0.1.0.dist-info/LICENSE
WinAPIClient-0.1.0.dist-info/METADATA
WinAPIClient-0.1.0.dist-info/WHEEL
WinAPIClient-0.1.0.dist-info/top_level.txt
WinAPIClient-0.1.0.dist-info/RECORD
