Metadata-Version: 2.1
Name: WinAPIClient
Version: 0.1.0
Summary: High-level wrapper around pywin32 for developing windows overlays
Home-page: https://github.com/ThomasSelvig/WinAPIClient
Author: Thomas Selvig
License: UNKNOWN
Platform: UNKNOWN
Classifier: Programming Language :: Python :: 3
Classifier: License :: OSI Approved :: MIT License
Classifier: Operating System :: Microsoft :: Windows :: Windows 10
Requires-Python: >=3.6
License-File: LICENSE
